libss/__init__.py
libss/separation/__init__.py
libss/separation/auxiva.py
libss/separation/metrics.py
libss/separation/update_rules.py
libss/separation/utils.py
libss-0.1.0.dist-info/LICENSE
libss-0.1.0.dist-info/WHEEL
libss-0.1.0.dist-info/METADATA
libss-0.1.0.dist-info/RECORD
