Metadata-Version: 2.1
Name: libss
Version: 0.1.0
Summary: Independent-component-analysis-based Blind audio source separation library.
Home-page: https://github.com/taishi-n/bliss
License: MIT
Author: Taishi Nakashima
Author-email: taishi@ieee.org
Requires-Python: >=3.8,<4.0
Classifier: License :: OSI Approved :: MIT License
Classifier: Programming Language :: Python :: 3
Classifier: Programming Language :: Python :: 3.8
Classifier: Programming Language :: Python :: 3.9
Requires-Dist: matplotlib (>=3.4.2,<4.0.0)
Requires-Dist: museval (>=0.4.0,<0.5.0)
Requires-Dist: numpy (>=1.20.3,<2.0.0)
Requires-Dist: pytest (>=6.2.4,<7.0.0)
Project-URL: Repository, https://github.com/taishi-n/bliss
